accuasset/__init__.py
accuasset/__prop__.py
accuasset/domain/__init__.py
accuasset/domain/eda/NanumGothic.ttf
accuasset/domain/eda/__init__.py
accuasset/domain/eda/visualize.py
accuasset/domain/nlp/__init__.py
accuasset/domain/nlp/model.py
accuasset/domain/nlp/preprocessing.py
accuasset/ds/__init__.py
accuasset/ds/tsdpy/__init__.py
accuasset/ds/tsqty/__init__.py
accuasset/ds/tsqty/ssp/__init__.py
accuasset/ds/tsqty/ssp/eda.py
accuasset/ds/tsqty/ssp/feature.py
accuasset/ds/tsqty/ssp/model.py
accuasset/ds/tsqty/ssp/prep.py
accuasset/ds/tsqty/ssp/util.py
test/__init__.py
test/ds_function/__init__.py
test/ds_function/test_ssp.py
test/general_function/__init__.py
test/general_function/test_domain_eda.py
accuasset-0.0.0.10.dist-info/LICENSE
accuasset-0.0.0.10.dist-info/METADATA
accuasset-0.0.0.10.dist-info/WHEEL
accuasset-0.0.0.10.dist-info/top_level.txt
accuasset-0.0.0.10.dist-info/RECORD
